ssdts_matching/__init__.py
ssdts_matching/_version.py
ssdts_matching/core.py
ssdts_matching-0.0.3.dist-info/DESCRIPTION.rst
ssdts_matching-0.0.3.dist-info/METADATA
ssdts_matching-0.0.3.dist-info/RECORD
ssdts_matching-0.0.3.dist-info/WHEEL
ssdts_matching-0.0.3.dist-info/metadata.json
ssdts_matching-0.0.3.dist-info/top_level.txt
