Metadata-Version: 2.0
Name: ssdts-matching
Version: 0.0.3
Summary: Fast matching of source-sharing derivative time series.
Home-page: https://github.com/shaypal5/ssdts_matching
Author: Shay Palachy
Author-email: shaypal5@gmail.com
License: MIT
Keywords: pandas dataframe pipeline data
Platform: any
Classifier: Development Status :: 4 - Beta
Classifier: License :: OSI Approved :: MIT License
Classifier: Programming Language :: Python
Classifier: Programming Language :: Python :: 3.5
Classifier: Programming Language :: Python :: 3.6
Classifier: Topic :: Software Development :: Libraries
Classifier: Topic :: Software Development :: Libraries :: Python Modules
Classifier: Intended Audience :: Developers
Requires-Dist: numpy
Requires-Dist: sortedcontainers
Provides-Extra: test
Requires-Dist: pytest; extra == 'test'
Requires-Dist: coverage; extra == 'test'
Requires-Dist: pytest-cov; extra == 'test'
